{
    "cam_analytics": "ibmcb-docker-local.artifactory.swg-devops.com/cam_analytics:release-2019.06.12-effcbdb-3680",
    "cam_apiserver": "ibmcb-docker-local.artifactory.swg-devops.com/cam_apiserver:release-2019.06.12-dec57f6-4721",
    "cam_aws_extractor": "ibmcb-docker-local.artifactory.swg-devops.com/cam-aws-extractor:release-2019.06.12-0cc71ef-1887",
    "cam_aws_ri_report": "ibmcb-docker-local.artifactory.swg-devops.com/cam-aws-ri-report:release-2019.06.12-b4ba14c-336",
    "cam_bootstrap": "ibmcb-docker-local.artifactory.swg-devops.com/cam_bootstrap:release-2019.06.12-02cf477-1066",
    "cam_db_backup": "ibmcb-docker-local.artifactory.swg-devops.com/cam-db-backup:release-2019.06.12-777d19e-295",
    "cam_gcp_extractor": "ibmcb-docker-local.artifactory.swg-devops.com/cam-gcp-extractor:release-2019.06.12-6517778-2309",
    "cam_migrator": "ibmcb-docker-local.artifactory.swg-devops.com/cam-migrator:release-2019.06.12-c564af0-2632",
    "cam_orchestrator_v2": "ibmcb-docker-local.artifactory.swg-devops.com/cam_orchestrator_v2:release-2019.06.12-baead79-6064",
    "cam_recommendation_engine": "ibmcb-docker-local.artifactory.swg-devops.com/cam_recommendation_engine:release-2019.06.12-26f2e1d-1264",
    "cam_services": "ibmcb-docker-local.artifactory.swg-devops.com/cam_services:release-2019.06.12-b838238-9067",
    "cam_softlayer_extractor": "ibmcb-docker-local.artifactory.swg-devops.com/cam-softlayer-extractor:release-2019.06.12-df22dcd-1885",
    "cam_spark": "ibmcb-docker-local.artifactory.swg-devops.com/cam-spark:release-2019.06.12-a25e453-68",
    "cam_task_manager": "ibmcb-docker-local.artifactory.swg-devops.com/cam-task-manager:release-2019.06.12-ff6495a-709",
    "cam_ui": "ibmcb-docker-local.artifactory.swg-devops.com/cam_ui:release-2019.06.12-7f9024b-18450",
    "cb_azure_extract": "ibmcb-docker-local.artifactory.swg-devops.com/cb-azure-extract:release-2019.06.12-f878638-1422",
    "cb_cam_diagnostics": "ibmcb-docker-local.artifactory.swg-devops.com/cb-cam-diagnostics:release-2019.06.12-327e9e1-326",
    "cb_nginx": "ibmcb-docker-local.artifactory.swg-devops.com/cb-nginx:release-2019.06.12-905665d-31",
    "cb_postgresql_v11": "ibmcb-docker-local.artifactory.swg-devops.com/cb-postgresql-v11:release-2019.06.12-3ceb618-3",
    "cb_rabbitmq": "ibmcb-docker-local.artifactory.swg-devops.com/cb-rabbitmq:release-2019.06.12-e06e996-87",
    "ha_mariadb": "ibmcb-docker-local.artifactory.swg-devops.com/ha-mariadb:release-2019.06.12-c9a833c-54",
    "k8_jumpbox": "ibmcb-docker-local.artifactory.swg-devops.com/k8-jumpbox:release-2019.06.12-da339fa-81",
    "k8s_mariadb": "ibmcb-docker-local.artifactory.swg-devops.com/k8s-mariadb:release-2019.06.12-1fcc8dc-152",
    "mariadb_xtrabackup": "ibmcb-docker-local.artifactory.swg-devops.com/mariadb-xtrabackup:release-2019.06.12-da501e8-40"
}